[
  {
    "id": "0",
    "page": "Porkcutlet",
    "Link": "/porkcutlet"
  },
  {
    "id": "1",
    "page": "Chinesefood",
    "Link": "/chinesefood"
  },
  {
    "id": "2",
    "page": "Chicken",
    "Link": "/chicken"
  },
  {
    "id": "3",
    "page": "Rice",
    "Link": "/rice"
  },
  {
    "id": "4",
    "page": "Cafe",
    "Link": "/cafe"
  },
  {
    "id": "5",
    "page": "Schoolfood",
    "Link": "/schoolfood"
  },
  {
    "id": "6",
    "page": "Stew",
    "Link": "/stew"
  },
  {
    "id": "7",
    "page": "Pizza",
    "Link": "/pizza"
  },
  {
    "id": "8",
    "page": "Westernfood",
    "Link": "/westernfood"
  },
  {
    "id": "9",
    "page": "Grilledmeat",
    "Link": "/grilledmeat"
  },
  {
    "id": "10",
    "page": "Jokbalandbossam",
    "Link": "/jokbalandbossam"
  },
  {
    "id": "11",
    "page": "Asian",
    "Link": "/asian"
  },
  {
    "id": "12",
    "page": "Fastfood",
    "Link": "/fastfood"
  },
  {
    "id": "13",
    "page": "Midnightmeal",
    "Link": "/midnightmeal"
  },
  {
    "id": "14",
    "page": "Boxlunch",
    "Link": "/boxlunch"
  }
]
